codebench/GitHandler.py
codebench/__init__.py
codebench/main.py
codebench/parsing/DefaultArgParser.py
codebench/parsing/__init__.py
codebench/performance/Runner.py
codebench/performance/__init__.py
codebench/report/ChartReporter.py
codebench/report/Factory.py
codebench/report/Reporter.py
codebench/report/__init__.py
codebench-0.0.2.dist-info/LICENSE
codebench-0.0.2.dist-info/METADATA
codebench-0.0.2.dist-info/WHEEL
codebench-0.0.2.dist-info/entry_points.txt
codebench-0.0.2.dist-info/top_level.txt
codebench-0.0.2.dist-info/RECORD
