Metadata-Version: 2.1
Name: codebench
Version: 0.0.2
Summary: Automated code benchmark solution
Home-page: https://github.com/li-boxuan/codebench
Author: Boxuan Li
Author-email: liboxuan@connect.hku.hk
License: UNKNOWN
Platform: UNKNOWN
Classifier: Programming Language :: Python :: 2
Classifier: Programming Language :: Python :: 2.7
Classifier: Programming Language :: Python :: 3
Classifier: Programming Language :: Python :: 3.5
Classifier: Programming Language :: Python :: 3.6
Classifier: Programming Language :: Python :: 3.7
Classifier: License :: OSI Approved :: MIT License
Classifier: Operating System :: OS Independent
Requires-Dist: GitPython
Requires-Dist: psutil
Requires-Dist: pyecharts
